django_middlewall-0.1.2.dist-info/DESCRIPTION.rst
django_middlewall-0.1.2.dist-info/METADATA
django_middlewall-0.1.2.dist-info/RECORD
django_middlewall-0.1.2.dist-info/WHEEL
django_middlewall-0.1.2.dist-info/metadata.json
django_middlewall-0.1.2.dist-info/top_level.txt
middlewall/__init__.py
middlewall/apps.py
middlewall/middleware.py
middlewall/utils.py
