Metadata-Version: 2.0
Name: django-middlewall
Version: 0.1.2
Summary: Simple middleware for filtering requests by their source IP address
Home-page: https://github.com/jmz-b/django-middlewall
Author: jmz
Author-email: jmz-b@users.noreply.github.com
License: BSD
Keywords: django-middlewall
Platform: UNKNOWN
Classifier: Development Status :: 3 - Alpha
Classifier: Framework :: Django
Classifier: Framework :: Django :: 1.8
Classifier: Framework :: Django :: 1.9
Classifier: Framework :: Django :: 1.10
Classifier: Intended Audience :: Developers
Classifier: License :: OSI Approved :: BSD License
Classifier: Natural Language :: English
Classifier: Programming Language :: Python :: 2
Classifier: Programming Language :: Python :: 2.7
Classifier: Programming Language :: Python :: 3
Classifier: Programming Language :: Python :: 3.3
Classifier: Programming Language :: Python :: 3.4
Classifier: Programming Language :: Python :: 3.5
Requires-Dist: Django (<1.10,>=1.8)
Requires-Dist: netaddr (<0.8,>=0.7)
Provides-Extra: test
Requires-Dist: codecov (>=2.0.0); extra == 'test'
Requires-Dist: coverage (==4.3.4); extra == 'test'
Requires-Dist: flake8 (>=2.1.0); extra == 'test'
Requires-Dist: mock (>=1.0.1); extra == 'test'
Requires-Dist: tox (>=1.7.0); extra == 'test'
